django_mfa3-1.1.0.dist-info/licenses/LICENSE
mfa/__init__.py
mfa/admin.py
mfa/apps.py
mfa/decorators.py
mfa/forms.py
mfa/mail.py
mfa/middleware.py
mfa/mixins.py
mfa/models.py
mfa/settings.py
mfa/urls.py
mfa/views.py
mfa/locale/de/LC_MESSAGES/django.mo
mfa/locale/de/LC_MESSAGES/django.po
mfa/locale/fr/LC_MESSAGES/django.mo
mfa/locale/fr/LC_MESSAGES/django.po
mfa/methods/__init__.py
mfa/methods/fido2.py
mfa/methods/recovery.py
mfa/methods/totp.py
mfa/migrations/0001_initial.py
mfa/migrations/0002_mfakey_last_code.py
mfa/migrations/0003_alter_mfakey_method.py
mfa/migrations/0004_alter_mfakey_id.py
mfa/migrations/__init__.py
mfa/static/mfa/fido2.js
mfa/static/mfa/vendor/webauthn-json.browser-ponyfill.js
mfa/templates/mfa/auth_FIDO2.html
mfa/templates/mfa/auth_TOTP.html
mfa/templates/mfa/auth_recovery.html
mfa/templates/mfa/create_FIDO2.html
mfa/templates/mfa/create_TOTP.html
mfa/templates/mfa/create_recovery.html
mfa/templates/mfa/login_failed_subject.txt
mfa/templates/mfa/mfakey_confirm_delete.html
mfa/templates/mfa/mfakey_list.html
mfa/templatetags/__init__.py
mfa/templatetags/mfa.py
django_mfa3-1.1.0.dist-info/METADATA
django_mfa3-1.1.0.dist-info/WHEEL
django_mfa3-1.1.0.dist-info/top_level.txt
django_mfa3-1.1.0.dist-info/RECORD
