Metadata-Version: 2.4
Name: django-mfa3
Version: 1.1.0
Summary: multi factor authentication for django
Author-email: Tobias Bengfort <tobias.bengfort@posteo.de>
License-Expression: MIT
Project-URL: Homepage, https://github.com/xi/django-mfa3
Keywords: django,mfa,two-factor-authentication,webauthn,fido2
Classifier: Development Status :: 5 - Production/Stable
Classifier: Environment :: Web Environment
Classifier: Framework :: Django
Classifier: Intended Audience :: Developers
Classifier: Operating System :: OS Independent
Classifier: Programming Language :: Python
Classifier: Programming Language :: Python :: 3
License-File: LICENSE
Requires-Dist: pyotp
Requires-Dist: fido2<3.0,>=2.0
Requires-Dist: qrcode<7.4,>=7.1
Requires-Dist: django>=4.2
Dynamic: license-file
